euroleague_api/EuroLeagueData.py
euroleague_api/__init__.py
euroleague_api/boxscore_data.py
euroleague_api/game_metadata.py
euroleague_api/game_stats.py
euroleague_api/play_by_play_data.py
euroleague_api/player_stats.py
euroleague_api/shot_data.py
euroleague_api/standings.py
euroleague_api/team_stats.py
euroleague_api/utils.py
euroleague_api-0.0.21.dist-info/METADATA
euroleague_api-0.0.21.dist-info/WHEEL
euroleague_api-0.0.21.dist-info/top_level.txt
euroleague_api-0.0.21.dist-info/RECORD
