Metadata-Version: 2.4
Name: euroleague_api
Version: 0.0.21
Summary: A Python wrapper of the Euroleague API
Home-page: https://github.com/giasemidis/euroleague_api
Download-URL: https://github.com/giasemidis/euroleague_api/archive/refs/tags/v0.0.21.tar.gz
Author: Georgios Giasemidis
Author-email: g.giasemidis@gmail.com
License: GPLv3 (with Commercial License option)
Keywords: euroleague,api,basketball
Classifier: License :: OSI Approved :: GNU General Public License v3 (GPLv3)
Classifier: License :: Other/Proprietary License
Requires-Python: >=3.6
Requires-Dist: requests
Requires-Dist: pandas
Requires-Dist: numpy
Requires-Dist: xmltodict
Requires-Dist: tqdm
Dynamic: download-url
